geometor/model/__init__.py
geometor/model/__main__.py
geometor/model/ancestors.py
geometor/model/chains.py
geometor/model/circles.py
geometor/model/colors.py
geometor/model/delete.py
geometor/model/element.py
geometor/model/helpers.py
geometor/model/lines.py
geometor/model/model.py
geometor/model/points.py
geometor/model/polygons.py
geometor/model/polynomials.py
geometor/model/reports.py
geometor/model/sections.py
geometor/model/segments.py
geometor/model/serialize.py
geometor/model/utils.py
geometor/model/wedges.py
geometor_model-0.5.0.dist-info/licenses/LICENSE
geometor_model-0.5.0.dist-info/METADATA
geometor_model-0.5.0.dist-info/WHEEL
geometor_model-0.5.0.dist-info/entry_points.txt
geometor_model-0.5.0.dist-info/top_level.txt
geometor_model-0.5.0.dist-info/RECORD
