Metadata-Version: 2.4
Name: geometor-model
Version: 0.5.0
Summary: A symbolic engine for defining and verifying geometric constructions.
Author-email: geometor <github@geometor.com>
Project-URL: Website, https://geometor.github.io/model
Project-URL: Repository, https://github.com/geometor/model
Project-URL: Issues, https://github.com/geometor/model/issues
Classifier: Programming Language :: Python :: 3
Classifier: License :: OSI Approved :: MIT License
Classifier: Operating System :: OS Independent
Requires-Python: >=3.13
License-File: LICENSE
Requires-Dist: sympy
Requires-Dist: rich
Provides-Extra: dev
Requires-Dist: pytest; extra == "dev"
Requires-Dist: matplotlib; extra == "dev"
Dynamic: license-file
